mmn_experiments/__init__.py
mmn_experiments/decorator.py
mmn_experiments/data/__init__.py
mmn_experiments/data/dades.py
mmn_experiments/database_model/__init__.py
mmn_experiments/database_model/database.py
mmn_experiments/experiment/__init__.py
mmn_experiments/experiment/experiment.py
mmn_experiments/keras/__init__.py
mmn_experiments/keras/telegramCallback.py
mmn_experiments-1.6.3.dist-info/LICENSE
mmn_experiments-1.6.3.dist-info/METADATA
mmn_experiments-1.6.3.dist-info/WHEEL
mmn_experiments-1.6.3.dist-info/top_level.txt
mmn_experiments-1.6.3.dist-info/RECORD
