Metadata-Version: 2.1
Name: mmn-experiments
Version: 1.6.3
Summary: Library to handle experiment information
Author-email: Miquel Miró Nicolau <miquel.miro@uib.cat>, Gabriel Moyà Alcover <gabriel_moya@uib.es>
Project-URL: Homepage, https://github.com/miquelmn/uib_experiments
Keywords: experiments,machine learning
Requires-Python: >=3.7
License-File: LICENSE
Requires-Dist: telegram-send
Requires-Dist: opencv-python
Requires-Dist: matplotlib
Requires-Dist: scipy
Requires-Dist: numpy
Requires-Dist: peewee
